{"is_source_file": true, "format": "TypeScript", "description": "Next.js configuration file defining the export settings for the Next.js project.", "external_files": ["next"], "external_methods": [], "published": ["default"], "classes": [], "methods": [{"name": "nextConfig", "description": "Configuration object specifying Next.js build options."}], "calls": ["export default"], "search-terms": ["next.config.ts", "NextConfig", "nextConfig", "export", "output"], "state": 2, "file_id": 4, "knowledge_revision": 19, "git_revision": "524dd7f918915ab9ad2581cdf80c594156c0914e", "ctags": [{"_type": "tag", "name": "nextConfig", "path": "/home/kavia/workspace/code-generation/gourmet-express-336032-336088/frontend_nextjs/next.config.ts", "pattern": "/^const nextConfig: NextConfig = {$/", "language": "TypeScript", "kind": "constant"}], "hash": "d2e8cb2378dd8f1f25150e4609f18db6", "format-version": 4, "code-base-name": "frontend_nextjs", "filename": "frontend_nextjs/next.config.ts", "revision_history": [{"19": "524dd7f918915ab9ad2581cdf80c594156c0914e"}]}